dclient/__init__.py
dclient/__main__.py
dclient/cli.py
dclient/plugin.py
dclient/utils.py
dclient-0.4.dist-info/LICENSE
dclient-0.4.dist-info/METADATA
dclient-0.4.dist-info/WHEEL
dclient-0.4.dist-info/entry_points.txt
dclient-0.4.dist-info/top_level.txt
dclient-0.4.dist-info/RECORD
