Metadata-Version: 2.1
Name: dclient
Version: 0.4
Summary: A client CLI utility for Datasette instances
Home-page: https://github.com/simonw/dclient
Author: Simon Willison
License: Apache License, Version 2.0
Project-URL: Issues, https://github.com/simonw/dclient/issues
Project-URL: CI, https://github.com/simonw/dclient/actions
Project-URL: Changelog, https://github.com/simonw/dclient/releases
Requires-Python: >=3.8
License-File: LICENSE
Requires-Dist: click
Requires-Dist: httpx
Requires-Dist: sqlite-utils
Provides-Extra: test
Requires-Dist: pytest ; extra == 'test'
Requires-Dist: pytest-asyncio ; extra == 'test'
Requires-Dist: pytest-httpx ; extra == 'test'
Requires-Dist: cogapp ; extra == 'test'
Requires-Dist: pytest-mock ; extra == 'test'
Requires-Dist: datasette >=1.0a2 ; extra == 'test'
